README.rst
setup.py
Eggsac.egg-info/PKG-INFO
Eggsac.egg-info/SOURCES.txt
Eggsac.egg-info/dependency_links.txt
Eggsac.egg-info/entry_points.txt
Eggsac.egg-info/not-zip-safe
Eggsac.egg-info/requires.txt
Eggsac.egg-info/top_level.txt
eggsac/__init__.py
eggsac/debian.py
eggsac/eggsac.py
eggsac/make_uwsgi_ini.py
eggsac/test_make_uwsgi_ini.py
eggsac/utils.py