Metadata-Version: 1.1
Name: Eggsac
Version: 0.1.0
Summary: Package Python applications in a virtualenv for deployment
Home-page: https://github.com/cozi/eggsac
Author: George V. Reilly
Author-email: george@reilly.org
License: MIT License
Platform: any
Classifier: Development Status :: 4 - Beta
Classifier: Environment :: Console
Classifier: Intended Audience :: Developers
Classifier: Intended Audience :: System Administrators
Classifier: License :: OSI Approved :: MIT License
Classifier: Operating System :: OS Independent
Classifier: Programming Language :: Python
Classifier: Topic :: System :: Installation/Setup
Classifier: Topic :: System :: Software Distribution
